README.txt
setup.py
db_class/__init__.py
db_class/db_class.py
db_class.egg-info/PKG-INFO
db_class.egg-info/SOURCES.txt
db_class.egg-info/dependency_links.txt
db_class.egg-info/requires.txt
db_class.egg-info/top_level.txt