Metadata-Version: 1.0
Name: db-class
Version: 0.3
Summary: db work class
Home-page: https://www.test.com
Author: EranArtzi
Author-email: eartzi@gmail.com
License: UNKNOWN
Platform: UNKNOWN
